{
  "main": {
    "id": "46ec1c64922acdb9",
    "type": "split",
    "children": [
      {
        "id": "16d7c889a5c72ef4",
        "type": "tabs",
        "children": [
          {
            "id": "ff866e3f24118294",
            "type": "leaf",
            "state": {
              "type": "excalidraw",
              "state": {
                "file": "Excalidraw/系统流程图.md"
              }
            }
          }
        ],
        "stacked": true
      }
    ],
    "direction": "vertical"
  },
  "left": {
    "id": "8382cecd0bb38b35",
    "type": "split",
    "children": [
      {
        "id": "0a68efb50c4989f9",
        "type": "tabs",
        "children": [
          {
            "id": "327624e3b2d79fdb",
            "type": "leaf",
            "state": {
              "type": "file-explorer",
              "state": {
                "sortOrder": "alphabetical"
              }
            }
          },
          {
            "id": "86490d83a2fc5222",
            "type": "leaf",
            "state": {
              "type": "search",
              "state": {
                "query": "tag:#32comment",
                "matchingCase": false,
                "explainSearch": false,
                "collapseAll": false,
                "extraContext": false,
                "sortOrder": "alphabetical"
              }
            }
          },
          {
            "id": "4d51a57e7b40a1e2",
            "type": "leaf",
            "state": {
              "type": "starred",
              "state": {}
            }
          }
        ]
      }
    ],
    "direction": "horizontal",
    "width": 300
  },
  "right": {
    "id": "a53911e798837b64",
    "type": "split",
    "children": [
      {
        "id": "9311f25433e3c498",
        "type": "tabs",
        "children": [
          {
            "id": "2c7e0dabea56d9aa",
            "type": "leaf",
            "state": {
              "type": "backlink",
              "state": {
                "file": "Excalidraw/系统流程图.md",
                "collapseAll": false,
                "extraContext": false,
                "sortOrder": "alphabetical",
                "showSearch": false,
                "searchQuery": "",
                "backlinkCollapsed": false,
                "unlinkedCollapsed": true
              }
            }
          },
          {
            "id": "e1c2d72580d98b60",
            "type": "leaf",
            "state": {
              "type": "outgoing-link",
              "state": {
                "file": "Excalidraw/系统流程图.md",
                "linksCollapsed": false,
                "unlinkedCollapsed": true
              }
            }
          },
          {
            "id": "061b563428c70e6a",
            "type": "leaf",
            "state": {
              "type": "tag",
              "state": {
                "sortOrder": "frequency",
                "useHierarchy": true
              }
            }
          },
          {
            "id": "231ca563937e09e0",
            "type": "leaf",
            "state": {
              "type": "outline",
              "state": {
                "file": "Excalidraw/系统流程图.md"
              }
            }
          },
          {
            "id": "22ddd35e8f383527",
            "type": "leaf",
            "state": {
              "type": "git-view",
              "state": {}
            }
          }
        ],
        "currentTab": 3
      }
    ],
    "direction": "horizontal",
    "width": 318.5
  },
  "left-ribbon": {
    "hiddenItems": {
      "switcher:打开快速切换": false,
      "graph:查看关系图谱": false,
      "canvas:新建白板": false,
      "daily-notes:打开/创建今天的日记": false,
      "templates:插入模板": false,
      "command-palette:打开命令面板": false,
      "obsidian-excalidraw-plugin:新建 Excalidraw 绘图": false
    }
  },
  "active": "ff866e3f24118294",
  "lastOpenFiles": [
    "Excalidraw/系统流程图.png",
    "source/_posts/FOC.md",
    "db.json",
    "public/uploads/avatar.png",
    "public/uploads",
    "public/lib/velocity/velocity.ui.min.js",
    "public/lib/velocity/velocity.min.js",
    "public/lib/velocity",
    "public/js/schemes/pisces.js",
    "public/js/schemes/muse.js",
    "public/js/schemes",
    "public/images/logo.svg",
    "public/images/favicon-32x32-next.png",
    "public/images/favicon-16x16-next.png",
    "public/images/cc-by.svg",
    "public/images/cc-zero.svg",
    "public/images/cc-by-sa.svg",
    "public/images/cc-by-nd.svg",
    "public/images/cc-by-nc.svg",
    "public/images/cc-by-nc-sa.svg",
    "public/css/injector/light.css",
    "public/index.html",
    "scaffolds/draft.md",
    "scaffolds/post.md",
    "Excalidraw/FOC整体框图.md",
    "Excalidraw/Clark变换.md",
    "Excalidraw/系统流程图.md",
    "未命名.md",
    "source/_posts/hello-world.md",
    "scaffolds/page.md",
    "themes/landscape/README.md",
    "blog/themes/landscape/README.md",
    "blog/source/_posts/hello-world.md",
    "blog/scaffolds/post.md",
    "blog/scaffolds/page.md",
    "blog/scaffolds/draft.md",
    "fcc.md",
    "未命名 1.md",
    "未命名 2.md",
    "未命名 3.md"
  ]
}